pop_up_ide/__init__.py
pop_up_ide/main.py
pop_up_ide/utils.py
pop_up_ide-0.1.dist-info/LICENCE
pop_up_ide-0.1.dist-info/METADATA
pop_up_ide-0.1.dist-info/WHEEL
pop_up_ide-0.1.dist-info/RECORD
