Metadata-Version: 2.1
Name: pop-up-ide
Version: 0.1
Summary: A brief description of your package
Home-page: https://github.com/markuslahde/pop-up-ide
License: GPL-3.0-or-later
Author: Markus Lähde
Author-email: markuslahde@gmail.com
Requires-Python: >=3.7
Classifier: License :: OSI Approved :: GNU General Public License v3 or later (GPLv3+)
Classifier: Programming Language :: Python :: 3
Classifier: Programming Language :: Python :: 3.7
Classifier: Programming Language :: Python :: 3.8
Classifier: Programming Language :: Python :: 3.9
Classifier: Programming Language :: Python :: 3.10
Classifier: Programming Language :: Python :: 3.11
Classifier: Programming Language :: Python :: 3.12
Classifier: Programming Language :: Python :: 3.13
Requires-Dist: dill
Requires-Dist: prompt_toolkit
Requires-Dist: pygments
Project-URL: Repository, https://github.com/markuslahde/pop-up-ide
